starlette_skin/__init__.py
starlette_skin-0.1.0.dist-info/DESCRIPTION.rst
starlette_skin-0.1.0.dist-info/METADATA
starlette_skin-0.1.0.dist-info/RECORD
starlette_skin-0.1.0.dist-info/WHEEL
starlette_skin-0.1.0.dist-info/metadata.json
starlette_skin-0.1.0.dist-info/top_level.txt
