Metadata-Version: 2.0
Name: starlette-skin
Version: 0.1.0
Summary: a wrapper for starlette in order to code in a tornado-like way
Home-page: https://github.com/beforeicer/starlette-skin
Author: hoo
Author-email: beforeicer@126.com
License: BSD License
Keywords: starlette like tornado style
Platform: *nix
Requires-Dist: aioredis (>=1.2.0)
Requires-Dist: asyncpg (>=0.18.3)
Requires-Dist: starlette (>=0.11.4)
